valgrind.cpython-38-darwin.so
valgrind-0.0.0.dist-info/LICENSE
valgrind-0.0.0.dist-info/METADATA
valgrind-0.0.0.dist-info/WHEEL
valgrind-0.0.0.dist-info/top_level.txt
valgrind-0.0.0.dist-info/RECORD
