Metadata-Version: 2.1
Name: valgrind
Version: 0.0.0
Summary: Control callgrind instrumentation from Python.
Home-page: https://github.com/tekknolagi/valgrind
Author: Max Bernstein
Author-email: python@bernsteinbear.com
License-File: LICENSE
